voxws/backbone.py
voxws/model.py
voxws/protonet.py
voxws/util.py
voxws-1.0.1.dist-info/METADATA
voxws-1.0.1.dist-info/WHEEL
voxws-1.0.1.dist-info/top_level.txt
voxws-1.0.1.dist-info/RECORD
