Metadata-Version: 2.1
Name: voxws
Version: 1.0.1
Summary: Few Shot Language Agnostic Keyword Spotting (FSLAKWS) System
Home-page: https://github.com/Kou-shik2004/SIH-2024
Download-URL: https://pypi.org/project/voxws/
Author: Koushik S
Author-email: koushik20040804@gmail.com
License: Apache-2.0
Keywords: Keyword Spotting,Few-shot Learning,Deep Neural Network,Audio,Speech
Requires-Dist: torch
Requires-Dist: torchvision
Requires-Dist: torchaudio
Requires-Dist: timm
Requires-Dist: wget
Requires-Dist: librosa
